umbrela/__init__.py
umbrela/gpt_judge.py
umbrela/llm_judge.py
umbrela/osllm_judge.py
umbrela/vicuna_judge.py
umbrela/prompts/qrel_fewshot_bing.txt
umbrela/utils/__init__.py
umbrela/utils/common_utils.py
umbrela/utils/qrel_utils.py
umbrela-0.0.7.dist-info/LICENSE
umbrela-0.0.7.dist-info/METADATA
umbrela-0.0.7.dist-info/WHEEL
umbrela-0.0.7.dist-info/top_level.txt
umbrela-0.0.7.dist-info/RECORD
