Metadata-Version: 2.1
Name: umbrela
Version: 0.0.7
Summary: A Package for generating query-passage relevance assessment labels.
Author-email: Shivani Upadhyay <sjupadhyay@uwaterloo.ca>, Ronak Pradeep <rpradeep@uwaterloo.ca>, Jimmy Lin <jimmylin@uwaterloo.ca>
License: 
Project-URL: Homepage, https://github.com/castorini/umbrela
Keywords: LLM,evaluation,information retrieval
Classifier: Programming Language :: Python
Classifier: Programming Language :: Python :: 3
Requires-Python: >=3.10
License-File: LICENSE
Requires-Dist: datasets >=2.19.0
Requires-Dist: fschat >=0.2.36
Requires-Dist: openai >=1.24.1
Requires-Dist: pyserini >=0.35.0
Requires-Dist: torch >=2.2.2
Requires-Dist: tqdm >=4.66.2
Requires-Dist: transformers >=4.40.1
